[
  {
    "id": 1001,
    "name": "Fresh-Whiped-Cream",
    "price": 41,
    "description": "Description here",
    "tastes": ["Mango", "Strawberry", "None-(Fresh-Milk)"],
    "productImage": "fresh.jpg",
    "categoryId": 1
  },
  {
    "id": 1002,
    "name": "Lotus",
    "price": 45,
    "description": "Description here",
    "tastes": [],
    "productImage": "lotus_cake.jpg",
    "categoryId": 1
  },
  {
    "id": 1003,
    "name": "Kabocha-Cheese",
    "price": 45,
    "description": "Description here",
    "tastes": [],
    "productImage": "pumpkin_cake.jpg",
    "categoryId": 1
  },
  {
    "id": 1004,
    "name": "Mugwort-Cake",
    "price": 45,
    "description": "Description here",
    "tastes": [],
    "productImage": "ssook.jpg",
    "categoryId": 1
  },
  {
    "id": 1005,
    "name": "Carrot-Cake",
    "price": 0,
    "description": "Description here",
    "tastes": [],
    "productImage": "carrot.jpg",
    "categoryId": 1
  },
  {
    "id": 1006,
    "name": "Black-Sesame-Cake",
    "price": 45,
    "description": "Description here",
    "tastes": [],
    "productImage": "cake_3.jpg",
    "categoryId": 1
  },
  {
    "id": 1007,
    "name": "Injeolmi-Cake",
    "price": 45,
    "description": "Description here",
    "tastes": [],
    "productImage": "cake_1.jpg",
    "categoryId": 1
  },
  {
    "id": 1008,
    "name": "Design-Cake",
    "price": 0,
    "description": "Description here",
    "tastes": [],
    "productImage": "whip-letter.jpg",
    "categoryId": 1
  },
  {
    "id": 1009,
    "name": "Flower-Cake",
    "price": 0,
    "description": "Description here",
    "tastes": [],
    "productImage": "custom.jpg",
    "categoryId": 1
  },
  {
    "id": 2001,
    "name": "Dacquoise-Set",
    "price": 20,
    "description": "Description here",
    "tastes": [
      "Cafe-Latte",
      "dacquoise-set",
      "Choco-Nutella",
      "Black-Sesame",
      "Lotus",
      "Cheese",
      "Ang-Butter"
    ],
    "productImage": "dac_set.jpg",
    "categoryId": 2
  },
  {
    "id": 2002,
    "name": "Injeolmi",
    "price": 4.1,
    "description": "Description here",
    "tastes": [],
    "productImage": "injeol.jpg",
    "categoryId": 2
  },

  {
    "id": 2003,
    "name": "Blueberry",
    "price": 3.9,
    "description": "Description here",
    "tastes": [],
    "productImage": "blue.jpg",
    "categoryId": 2
  },
  {
    "id": 2004,
    "name": "Earl-Grey",
    "price": 4.1,
    "description": "Description here",
    "tastes": [],
    "categoryId": 2,
    "productImage": "earl.jpg"
  },
  {
    "id": 2005,
    "name": "Cherry",
    "price": 3.9,
    "description": "Description here",
    "tastes": [],
    "productImage": "cherry.jpg",
    "categoryId": 2
  },
  {
    "id": 2006,
    "name": "Black-Sesame",
    "price": 4.1,
    "description": "Description here",
    "tastes": [],
    "productImage": "black.jpg",
    "categoryId": 2
  },
  {
    "id": 2007,
    "name": "Maltesers",
    "price": 3.7,
    "description": "Description here",
    "tastes": [],
    "productImage": "choco.jpg",
    "categoryId": 2
  },
  {
    "id": 2008,
    "name": "Lotus",
    "price": 4.0,
    "description": "Description here",
    "tastes": [],
    "productImage": "lotus.jpg",
    "categoryId": 2
  },
  {
    "id": 2009,
    "name": "Matcha-Kitkat",
    "price": 3.8,
    "description": "Description here",
    "tastes": [],
    "productImage": "matcha.jpg",
    "categoryId": 2
  },
  {
    "id": 2010,
    "name": "Oreo",
    "price": 4.0,
    "description": "Description here",
    "tastes": [],
    "productImage": "oreo.jpg",
    "categoryId": 2
  },
  {
    "id": 2011,
    "name": "Mugwort",
    "price": 3.9,
    "description": "Description here",
    "tastes": [],
    "productImage": "ssook_dac.jpg",
    "categoryId": 2
  },
  {
    "id": 2012,
    "name": "Sweet-Potato",
    "price": 4.1,
    "description": "Description here",
    "tastes": [],
    "productImage": "notyet.jpg",
    "categoryId": 2
  },

  {
    "id": 2013,
    "name": "Cafe-Latte",
    "price": 3.9,
    "description": "Description here",
    "tastes": [],
    "productImage": "cafem.jpg",
    "categoryId": 2
  },
  {
    "id": 2014,
    "name": "Salted-Caramel",
    "price": 3.7,
    "description": "Description here",
    "tastes": [],
    "productImage": "solti.jpg",
    "categoryId": 2
  },
  {
    "id": 2015,
    "name": "Tiramisu",
    "price": 4.1,
    "description": "Description here",
    "tastes": [],
    "productImage": "tira.jpg",
    "categoryId": 2
  },
  {
    "id": 2016,
    "name": "Bacon",
    "price": 3.7,
    "description": "Description here",
    "tastes": [],
    "productImage": "notyet.jpg",
    "categoryId": 2
  },
  {
    "id": 2017,
    "name": "Tok-Tok-Corn",
    "price": 4.0,
    "description": "Description here",
    "tastes": [],
    "productImage": "ccorn.jpg",
    "categoryId": 2
  },

  {
    "id": 2018,
    "name": "Ang-Butter",
    "price": 4.0,
    "description": "Description here",
    "tastes": [],
    "productImage": "notyet.jpg",
    "categoryId": 2
  },

  {
    "id": 2019,
    "name": "Cheese",
    "price": 4.0,
    "description": "Description here",
    "tastes": [],
    "productImage": "cheesep.jpg",
    "categoryId": 2
  },

  {
    "id": 2020,
    "name": "Chai-Latte",
    "price": 3.9,
    "description": "Description here",
    "tastes": [],
    "productImage": "notyet.jpg",
    "categoryId": 2
  },
  {
    "id": 2021,
    "name": "Match-Nutella",
    "price": 4.0,
    "description": "Description here",
    "tastes": [],
    "productImage": "notyet.jpg",
    "categoryId": 2
  },

  {
    "id": 2022,
    "name": "Citron",
    "price": 3.9,
    "description": "Description here",
    "tastes": [],
    "productImage": "notyet.jpg",
    "categoryId": 2
  },

  {
    "id": 2023,
    "name": "Yogurt",
    "price": 3.9,
    "description": "Description here",
    "tastes": [],
    "productImage": "notyet.jpg",
    "categoryId": 2
  },
  {
    "id": 2024,
    "name": "Choco-Nutella",
    "price": 3.9,
    "description": "Description here",
    "tastes": [],
    "productImage": "notyet.jpg",
    "categoryId": 2
  }
]
